setup.py
observe/__init__.py
observe/global_var.py
observe/observe.py
observe.egg-info/PKG-INFO
observe.egg-info/SOURCES.txt
observe.egg-info/dependency_links.txt
observe.egg-info/requires.txt
observe.egg-info/top_level.txt
observe/tests/__init__.py
observe/tests/test_observe.py