Metadata-Version: 1.1
Name: observe
Version: 0.0.3
Summary: A powerfull dataframe describer with pandas.
Home-page: UNKNOWN
Author: cph
Author-email: UNKNOWN
License: MIT
Platform: UNKNOWN
Classifier: Programming Language :: Python
Classifier: Programming Language :: Python :: 3.5
